cga2m_plus/.ipynb_checkpoints/cga2m-checkpoint.py
cga2m_plus/.ipynb_checkpoints/visualize-checkpoint.py
cga2m_plus/__init__.py
cga2m_plus/cga2m.py
cga2m_plus/visualize.py
cga2m_plus-0.1.10.dist-info/LICENSE
cga2m_plus-0.1.10.dist-info/WHEEL
cga2m_plus-0.1.10.dist-info/METADATA
cga2m_plus-0.1.10.dist-info/RECORD
