Metadata-Version: 2.1
Name: cga2m-plus
Version: 0.1.10
Summary: CGA2M_plus is a Python package of Constraint GA2M plus(CGA2M+). CGA2M+ is a model that improves GA2M in two respects: interpretability and accuracy.
Home-page: https://github.com/MK-tech20
License: MIT
Author: Michiya, Kuramata
Author-email: baisgtud43j@gmail.com
Requires-Python: >=3.7,<4.0
Classifier: Development Status :: 4 - Beta
Classifier: Intended Audience :: Science/Research
Classifier: License :: OSI Approved :: MIT License
Classifier: Programming Language :: Python :: 3
Classifier: Programming Language :: Python :: 3.7
Classifier: Programming Language :: Python :: 3.8
Classifier: Programming Language :: Python :: 3.9
Classifier: Topic :: Scientific/Engineering :: Artificial Intelligence
Requires-Dist: lightgbm (>=3.2.1,<4.0.0)
Requires-Dist: matplotlib (>=3.4.2,<4.0.0)
Requires-Dist: numpy
Requires-Dist: seaborn (>=0.11.1,<0.12.0)
Project-URL: Repository, https://github.com/MK-tech20/CGA2M_plus
